ynab_import/__init__.py
ynab_import/cli/__init__.py
ynab_import/cli/ascii_art.py
ynab_import/cli/menus.py
ynab_import/core/__init__.py
ynab_import/core/clean_input.py
ynab_import/core/config.py
ynab_import/core/data_converter.py
ynab_import/core/pipeline.py
ynab_import/core/preset.py
ynab_import/file_rw/__init__.py
ynab_import/file_rw/readers.py
ynab_import/file_rw/writers.py
ynab_converter-0.6.2.dist-info/METADATA
ynab_converter-0.6.2.dist-info/WHEEL
ynab_converter-0.6.2.dist-info/entry_points.txt
ynab_converter-0.6.2.dist-info/licenses/LICENSE
ynab_converter-0.6.2.dist-info/RECORD
