Metadata-Version: 2.4
Name: ynab-converter
Version: 0.6.2
Summary: A powerful CLI tool for converting bank export files to YNAB-compatible CSV format with interactive preset management
Project-URL: Homepage, https://github.com/pavelapekhtin/ynab-import
Project-URL: Repository, https://github.com/pavelapekhtin/ynab-import
Project-URL: Documentation, https://github.com/pavelapekhtin/ynab-import#readme
Project-URL: Bug Tracker, https://github.com/pavelapekhtin/ynab-import/issues
Project-URL: Changelog, https://github.com/pavelapekhtin/ynab-import/blob/main/CHANGELOG.md
Author-email: Pavel Apekhtin <pavelapekdev@gmail.com>
Maintainer-email: Pavel Apekhtin <pavelapekdev@gmail.com>
License: MIT License
License-File: LICENSE
Keywords: bank,budget,cli,converter,csv,finance,import,ynab
Classifier: Development Status :: 4 - Beta
Classifier: Environment :: Console
Classifier: Intended Audience :: End Users/Desktop
Classifier: License :: OSI Approved :: MIT License
Classifier: Operating System :: OS Independent
Classifier: Programming Language :: Python :: 3
Classifier: Programming Language :: Python :: 3.12
Classifier: Topic :: Office/Business :: Financial
Classifier: Topic :: Utilities
Classifier: Typing :: Typed
Requires-Python: >=3.12
Requires-Dist: ipykernel>=6.30.1
Requires-Dist: openpyxl>=3.1.0
Requires-Dist: pandas>=2.3.2
Requires-Dist: platformdirs>=4.0.0
Requires-Dist: pydantic>=2.11.9
Requires-Dist: questionary>=2.0.0
Requires-Dist: rich>=14.1.0
Requires-Dist: tomli-w>=1.0.0
Requires-Dist: tomli>=2.0.0
Requires-Dist: xlrd>=2.0.2
Provides-Extra: dev
Requires-Dist: build>=1.0.0; extra == 'dev'
Requires-Dist: commitizen>=3.0.0; extra == 'dev'
Requires-Dist: ipykernel; extra == 'dev'
Requires-Dist: pandas-stubs>=2.0.0; extra == 'dev'
Requires-Dist: pre-commit>=3.0.0; extra == 'dev'
Requires-Dist: pytest-cov>=7.0.0; extra == 'dev'
Requires-Dist: pytest>=8.4.2; extra == 'dev'
Requires-Dist: ruff; extra == 'dev'
Requires-Dist: twine>=4.0.0; extra == 'dev'
